odoo9_addon_l10n_es_aeat_mod296-9.0.1.0.0.99.dev7-py3.8-nspkg.pth
odoo_addons/l10n_es_aeat_mod296/README.rst
odoo_addons/l10n_es_aeat_mod296/__init__.py
odoo_addons/l10n_es_aeat_mod296/__openerp__.py
odoo_addons/l10n_es_aeat_mod296/data/aeat_export_mod296_data.xml
odoo_addons/l10n_es_aeat_mod296/data/aeat_export_mod296_line_data.xml
odoo_addons/l10n_es_aeat_mod296/data/tax_code_map_mod296_data.xml
odoo_addons/l10n_es_aeat_mod296/docs/DR296_2017.pdf
odoo_addons/l10n_es_aeat_mod296/docs/instrucciones_296.pdf
odoo_addons/l10n_es_aeat_mod296/docs/register_design_296_2008.pdf
odoo_addons/l10n_es_aeat_mod296/i18n/ca.po
odoo_addons/l10n_es_aeat_mod296/i18n/es.po
odoo_addons/l10n_es_aeat_mod296/i18n/l10n_es_aeat_mod296.pot
odoo_addons/l10n_es_aeat_mod296/models/__init__.py
odoo_addons/l10n_es_aeat_mod296/models/mod296.py
odoo_addons/l10n_es_aeat_mod296/readme/CONFIGURE.rst
odoo_addons/l10n_es_aeat_mod296/readme/CONTRIBUTORS.rst
odoo_addons/l10n_es_aeat_mod296/readme/DESCRIPTION.rst
odoo_addons/l10n_es_aeat_mod296/readme/USAGE.rst
odoo_addons/l10n_es_aeat_mod296/security/ir.model.access.csv
odoo_addons/l10n_es_aeat_mod296/security/ir_rule.xml
odoo_addons/l10n_es_aeat_mod296/static/description/icon.png
odoo_addons/l10n_es_aeat_mod296/static/description/icon_source.svg
odoo_addons/l10n_es_aeat_mod296/static/description/index.html
odoo_addons/l10n_es_aeat_mod296/tests/__init__.py
odoo_addons/l10n_es_aeat_mod296/tests/test_l10n_es_aeat_mod296.py
odoo_addons/l10n_es_aeat_mod296/views/mod296_views.xml
odoo9_addon_l10n_es_aeat_mod296-9.0.1.0.0.99.dev7.dist-info/METADATA
odoo9_addon_l10n_es_aeat_mod296-9.0.1.0.0.99.dev7.dist-info/WHEEL
odoo9_addon_l10n_es_aeat_mod296-9.0.1.0.0.99.dev7.dist-info/namespace_packages.txt
odoo9_addon_l10n_es_aeat_mod296-9.0.1.0.0.99.dev7.dist-info/top_level.txt
odoo9_addon_l10n_es_aeat_mod296-9.0.1.0.0.99.dev7.dist-info/RECORD
