Metadata-Version: 2.1
Name: odoo9-addon-l10n-es-aeat-mod296
Version: 9.0.1.0.0.99.dev7
Summary: AEAT modelo 296
Home-page: https://github.com/OCA/l10n-spain
Author: Tecnativa,AvanzOSC,Qubiq 2010 S.L,Odoo Community Association (OCA)
Author-email: support@odoo-community.org
License: AGPL-3
Platform: UNKNOWN
Classifier: Programming Language :: Python
Classifier: Framework :: Odoo
Classifier: Framework :: Odoo :: 9.0
Classifier: License :: OSI Approved :: GNU Affero General Public License v3
Requires-Python: ~=2.7
Requires-Dist: odoo9-addon-l10n-es-aeat
Requires-Dist: odoo9-addon-l10n-es-aeat-mod216
Requires-Dist: odoo (<9.1a,>=9.0a)
